pydantic_argparse_builder/__init__.py
pydantic_argparse_builder/__version__.py
pydantic_argparse_builder/cli.py
pydantic_argparse_builder/config.py
pydantic_argparse_builder/parse.py
pydantic_argparse_builder-0.3.1.dist-info/LICENSE
pydantic_argparse_builder-0.3.1.dist-info/METADATA
pydantic_argparse_builder-0.3.1.dist-info/WHEEL
pydantic_argparse_builder-0.3.1.dist-info/RECORD
