Metadata-Version: 2.1
Name: pydantic-argparse-builder
Version: 0.3.1
Summary: Build ArgumentParser from pydantic model.
License: Apache-2.0
Author: elda27
Author-email: kaz.birdstick@gmail.com
Requires-Python: >=3.8,<4.0
Classifier: License :: OSI Approved :: Apache Software License
Classifier: Programming Language :: Python :: 3
Classifier: Programming Language :: Python :: 3.8
Classifier: Programming Language :: Python :: 3.9
Classifier: Programming Language :: Python :: 3.10
Classifier: Programming Language :: Python :: 3.11
Requires-Dist: pydantic (>=2.0.0,<3.0.0)
Requires-Dist: pydantic-settings (>=2.0.2,<3.0.0)
